Workbook

Sheet About
A1: The Modern AI Concept Book
A2: Edition 2 · September 2026 · current to September 20, 2026
A4: How to filter
A5: Concepts sheet: one row per concept. Use the filter arrows on the header row to filter by Category, Since (year emerged), Status, Level or any Tag column (Yes/blank).
A6: Resources sheet: one row per resource link. Filter by Year, Type, Category, Level or Concept; click a URL to open it.
A7: Summary sheet: live counts by category, by year of emergence and by resource type/year (formulas recalculate if you add rows).
A9: Column notes
A10: Since = year the concept emerged. Active until = latest year of major change. Status: New in 2026, Active in 2026, or Established.
A11: Resource Year = publication year of an article, paper or spec, or launch year of a repository or site (approximate for long-running projects).
A12: Chapter 1 (Frontier Landscape) reflects public reporting as of September 20, 2026 and will date quickly.

Sheet Summary
A1: Live counts (recalculate automatically)
A3: Category | B3: Concepts | C3: New in 2026 | D3: Active in 2026 | E3: Resources
A4: 01. The Frontier Landscape (September 2026) | B4: =COUNTIFS(Concepts!$D:$D,$A4) | C4: =COUNTIFS(Concepts!$D:$D,$A4,Concepts!$G:$G,"New in 2026") | D4: =COUNTIFS(Concepts!$D:$D,$A4,Concepts!$G:$G,"<>Established") | E4: =COUNTIFS(Resources!$F:$F,$A4)
A5: 02. Agents and Harnesses | B5: =COUNTIFS(Concepts!$D:$D,$A5) | C5: =COUNTIFS(Concepts!$D:$D,$A5,Concepts!$G:$G,"New in 2026") | D5: =COUNTIFS(Concepts!$D:$D,$A5,Concepts!$G:$G,"<>Established") | E5: =COUNTIFS(Resources!$F:$F,$A5)
A6: 03. Protocols and Interoperability Standards | B6: =COUNTIFS(Concepts!$D:$D,$A6) | C6: =COUNTIFS(Concepts!$D:$D,$A6,Concepts!$G:$G,"New in 2026") | D6: =COUNTIFS(Concepts!$D:$D,$A6,Concepts!$G:$G,"<>Established") | E6: =COUNTIFS(Resources!$F:$F,$A6)
A7: 04. Agentic Coding and Developer Workflow | B7: =COUNTIFS(Concepts!$D:$D,$A7) | C7: =COUNTIFS(Concepts!$D:$D,$A7,Concepts!$G:$G,"New in 2026") | D7: =COUNTIFS(Concepts!$D:$D,$A7,Concepts!$G:$G,"<>Established") | E7: =COUNTIFS(Resources!$F:$F,$A7)
A8: 05. Context, Memory and Retrieval | B8: =COUNTIFS(Concepts!$D:$D,$A8) | C8: =COUNTIFS(Concepts!$D:$D,$A8,Concepts!$G:$G,"New in 2026") | D8: =COUNTIFS(Concepts!$D:$D,$A8,Concepts!$G:$G,"<>Established") | E8: =COUNTIFS(Resources!$F:$F,$A8)
A9: 06. Reasoning and Post-Training | B9: =COUNTIFS(Concepts!$D:$D,$A9) | C9: =COUNTIFS(Concepts!$D:$D,$A9,Concepts!$G:$G,"New in 2026") | D9: =COUNTIFS(Concepts!$D:$D,$A9,Concepts!$G:$G,"<>Established") | E9: =COUNTIFS(Resources!$F:$F,$A9)
A10: 07. Model Architectures | B10: =COUNTIFS(Concepts!$D:$D,$A10) | C10: =COUNTIFS(Concepts!$D:$D,$A10,Concepts!$G:$G,"New in 2026") | D10: =COUNTIFS(Concepts!$D:$D,$A10,Concepts!$G:$G,"<>Established") | E10: =COUNTIFS(Resources!$F:$F,$A10)
A11: 08. Training at Scale and Fine-Tuning | B11: =COUNTIFS(Concepts!$D:$D,$A11) | C11: =COUNTIFS(Concepts!$D:$D,$A11,Concepts!$G:$G,"New in 2026") | D11: =COUNTIFS(Concepts!$D:$D,$A11,Concepts!$G:$G,"<>Established") | E11: =COUNTIFS(Resources!$F:$F,$A11)
A12: 09. Inference and Serving | B12: =COUNTIFS(Concepts!$D:$D,$A12) | C12: =COUNTIFS(Concepts!$D:$D,$A12,Concepts!$G:$G,"New in 2026") | D12: =COUNTIFS(Concepts!$D:$D,$A12,Concepts!$G:$G,"<>Established") | E12: =COUNTIFS(Resources!$F:$F,$A12)
A13: 10. Quantization and Number Formats | B13: =COUNTIFS(Concepts!$D:$D,$A13) | C13: =COUNTIFS(Concepts!$D:$D,$A13,Concepts!$G:$G,"New in 2026") | D13: =COUNTIFS(Concepts!$D:$D,$A13,Concepts!$G:$G,"<>Established") | E13: =COUNTIFS(Resources!$F:$F,$A13)
A14: 11. AI Hardware, Interconnect and Datacenter Standards | B14: =COUNTIFS(Concepts!$D:$D,$A14) | C14: =COUNTIFS(Concepts!$D:$D,$A14,Concepts!$G:$G,"New in 2026") | D14: =COUNTIFS(Concepts!$D:$D,$A14,Concepts!$G:$G,"<>Established") | E14: =COUNTIFS(Resources!$F:$F,$A14)
A15: 12. Vision-Language and Multimodal Models | B15: =COUNTIFS(Concepts!$D:$D,$A15) | C15: =COUNTIFS(Concepts!$D:$D,$A15,Concepts!$G:$G,"New in 2026") | D15: =COUNTIFS(Concepts!$D:$D,$A15,Concepts!$G:$G,"<>Established") | E15: =COUNTIFS(Resources!$F:$F,$A15)
... A20: 17. Keep Learning: Curated Resources | B20: =COUNTIFS(Concepts!$D:$D,$A20) | C20: =COUNTIFS(Concepts!$D:$D,$A20,Concepts!$G:$G,"New in 2026") | D20: =COUNTIFS(Concepts!$D:$D,$A20,Concepts!$G:$G,"<>Established") | E20: =COUNTIFS(Resources!$F:$F,$A20)
A21: Total | B21: =SUM(B4:B20) | C21: =SUM(C4:C20) | D21: =SUM(D4:D20) | E21: =SUM(E4:E20)
A23: Year | B23: Concepts emerged | C23: Resources published
A24: 2026 | B24: =COUNTIFS(Concepts!$E:$E,$A24) | C24: =COUNTIFS(Resources!$A:$A,$A24)
A25: 2025 | B25: =COUNTIFS(Concepts!$E:$E,$A25) | C25: =COUNTIFS(Resources!$A:$A,$A25)
A26: 2024 | B26: =COUNTIFS(Concepts!$E:$E,$A26) | C26: =COUNTIFS(Resources!$A:$A,$A26)
A27: 2023 | B27: =COUNTIFS(Concepts!$E:$E,$A27) | C27: =COUNTIFS(Resources!$A:$A,$A27)
A28: 2022 | B28: =COUNTIFS(Concepts!$E:$E,$A28) | C28: =COUNTIFS(Resources!$A:$A,$A28)
A29: 2021 | B29: =COUNTIFS(Concepts!$E:$E,$A29) | C29: =COUNTIFS(Resources!$A:$A,$A29)
A30: 2020 | B30: =COUNTIFS(Concepts!$E:$E,$A30) | C30: =COUNTIFS(Resources!$A:$A,$A30)
A31: 2019 | B31: =COUNTIFS(Concepts!$E:$E,$A31) | C31: =COUNTIFS(Resources!$A:$A,$A31)
A32: 2018 | B32: =COUNTIFS(Concepts!$E:$E,$A32) | C32: =COUNTIFS(Resources!$A:$A,$A32)
A33: 2017 | B33: =COUNTIFS(Concepts!$E:$E,$A33) | C33: =COUNTIFS(Resources!$A:$A,$A33)
A34: Before 2017 | B34: =COUNTIFS(Concepts!$E:$E,"<2017") | C34: =COUNTIFS(Resources!$A:$A,"<2017")
A36: Resource type | B36: All years | C36: 2026 | D36: 2025 | E36: 2024 | F36: Before 2024
A37: GitHub | B37: =COUNTIFS(Resources!$B:$B,$A37) | C37: =COUNTIFS(Resources!$B:$B,$A37,Resources!$A:$A,2026) | D37: =COUNTIFS(Resources!$B:$B,$A37,Resources!$A:$A,2025) | E37: =COUNTIFS(Resources!$B:$B,$A37,Resources!$A:$A,2024) | F37: =COUNTIFS(Resources!$B:$B,$A37,Resources!$A:$A,"<2024")
A38: Blog | B38: =COUNTIFS(Resources!$B:$B,$A38) | C38: =COUNTIFS(Resources!$B:$B,$A38,Resources!$A:$A,2026) | D38: =COUNTIFS(Resources!$B:$B,$A38,Resources!$A:$A,2025) | E38: =COUNTIFS(Resources!$B:$B,$A38,Resources!$A:$A,2024) | F38: =COUNTIFS(Resources!$B:$B,$A38,Resources!$A:$A,"<2024")
A39: Paper | B39: =COUNTIFS(Resources!$B:$B,$A39) | C39: =COUNTIFS(Resources!$B:$B,$A39,Resources!$A:$A,2026) | D39: =COUNTIFS(Resources!$B:$B,$A39,Resources!$A:$A,2025) | E39: =COUNTIFS(Resources!$B:$B,$A39,Resources!$A:$A,2024) | F39: =COUNTIFS(Resources!$B:$B,$A39,Resources!$A:$A,"<2024")
A40: Docs | B40: =COUNTIFS(Resources!$B:$B,$A40) | C40: =COUNTIFS(Resources!$B:$B,$A40,Resources!$A:$A,2026) | D40: =COUNTIFS(Resources!$B:$B,$A40,Resources!$A:$A,2025) | E40: =COUNTIFS(Resources!$B:$B,$A40,Resources!$A:$A,2024) | F40: =COUNTIFS(Resources!$B:$B,$A40,Resources!$A:$A,"<2024")
A41: Spec | B41: =COUNTIFS(Resources!$B:$B,$A41) | C41: =COUNTIFS(Resources!$B:$B,$A41,Resources!$A:$A,2026) | D41: =COUNTIFS(Resources!$B:$B,$A41,Resources!$A:$A,2025) | E41: =COUNTIFS(Resources!$B:$B,$A41,Resources!$A:$A,2024) | F41: =COUNTIFS(Resources!$B:$B,$A41,Resources!$A:$A,"<2024")
A42: Video | B42: =COUNTIFS(Resources!$B:$B,$A42) | C42: =COUNTIFS(Resources!$B:$B,$A42,Resources!$A:$A,2026) | D42: =COUNTIFS(Resources!$B:$B,$A42,Resources!$A:$A,2025) | E42: =COUNTIFS(Resources!$B:$B,$A42,Resources!$A:$A,2024) | F42: =COUNTIFS(Resources!$B:$B,$A42,Resources!$A:$A,"<2024")
A44: Level | B44: Concepts
A45: Beginner | B45: =COUNTIFS(Concepts!$H:$H,$A45)
A46: Intermediate | B46: =COUNTIFS(Concepts!$H:$H,$A46)
A47: Advanced | B47: =COUNTIFS(Concepts!$H:$H,$A47)

Sheet Concepts
A1: No. | B1: Concept | C1: Alias | D1: Category | E1: Since | F1: Active until | G1: Status | H1: Level | I1: Foundational | J1: Production practice | K1: Research frontier | L1: Open source / open weights | M1: Open standard | N1: Enterprise | O1: Security | P1: Cost & efficiency | Q1: Definition | R1: Key points | S1: State of the art (Sept 2026) | T1: Resources
A2: 1 | B2: Mythos-class tier and trusted access | C2: Fable / Mythos | D2: 01. The Frontier Landscape (September 2026) | E2: 2026 | F2: 2026 | G2: New in 2026 | H2: Beginner | N2: Yes | O2: Yes | Q2: Anthropic introduced a capability tier above Opus. The same underlying model ships in two forms: Claude Fable for general use with extra safeguards in biology, cybersecurity and LLM R&D, and Claude Mythos for vetted defenders and partners through Project Glasswing. | R2: • Mythos Preview (April 2026) was first restricted to trusted organisations for cyber defense. • Fable 5 / Mythos 5 launched June 9, 2026; access was suspended June 12 to comply with US export controls and restored July 1 after the controls were lifted. • Fable 5.1 and Mythos 5.1 followed on September 1, 2026, with 1M-token context. | S2: Fable 5.1 is Anthropic's generally available flagship; Opus 5 (July 2026) and Sonnet 5 sit below it. | T2: 3
A3: 2 | B3: GPT-6 Astra and the Critical cyber threshold | C3: GPT-6 | D3: 01. The Frontier Landscape (September 2026) | E3: 2026 | F3: 2026 | G3: New in 2026 | H3: Beginner | N3: Yes | O3: Yes | Q3: OpenAI's first GPT-6 generation model, released September 3, 2026. It is the first model OpenAI classified at the Critical cybersecurity level of its Preparedness Framework, so it launched in phases with stronger safeguards and a trusted-access program for defenders. | R3: • Critical means the model can find and exploit unknown vulnerabilities in hardened systems without step-by-step human guidance. • Public versions refuse advanced offensive tasks; vetted defenders get more through OpenAI's trusted-access programs. • Its system card also reported reduced chain-of-thought monitorability, a notable safety signal. | S3: GPT-6 Astra sits above the GPT-5.6 Sol / Terra / Luna tiers. | T3: 4
A4: 3 | B4: Tiered access for dual-use models | C4: trusted access | D4: 01. The Frontier Landscape (September 2026) | E4: 2025 | F4: 2026 | G4: Active in 2026 | H4: Intermediate | N4: Yes | O4: Yes | Q4: A 2026 industry pattern: the most cyber-capable models are released in a public version with guardrails and a restricted version for vetted security teams and critical-infrastructure operators. | R4: • Anthropic (Glasswing), OpenAI (trusted access for cyber) and Google (defender-only cyber variants) all adopted versions of it. • It lets defenders patch vulnerabilities before equivalent capabilities spread. • Enterprises now need to track which model variant, safeguards and data-retention terms they are using. | T4: 2
A5: 4 | B5: Open-weight frontier models | D5: 01. The Frontier Landscape (September 2026) | E5: 2023 | F5: 2026 | G5: Active in 2026 | H5: Beginner | L5: Yes | P5: Yes | Q5: Open-weight models trail the closed frontier by months, not years. 2026's leading families are mostly large sparse MoEs with 1M-token context and permissive licences. | R5: • DeepSeek V4 (April 2026): Pro has 1.6T total / 49B active parameters, Flash has 284B / 13B, both with 1M context, MIT licence. • Other active families: Qwen 3.x, Kimi, GLM-5.x, MiniMax, Mistral Large 3, NVIDIA Nemotron 3, Google Gemma 4. • Open weight does not always mean open source: check licence terms and whether data and code are released. | S5: DeepSeek V4 is the reference open model for long-context efficiency; small open models now run strong coding workloads on a single GPU. | T5: 3
A6: 5 | B6: Model release trackers | D6: 01. The Frontier Landscape (September 2026) | E6: 2023 | F6: 2026 | G6: Active in 2026 | H6: Beginner | J6: Yes | Q6: In 2026 frontier labs shipped new models every few weeks. Trackers and independent benchmark aggregators are the practical way to keep up. | R6: • Compare on your own evals, not headline benchmarks. • Watch pricing changes as closely as capability changes: cache-read and small-tier prices fell sharply in 2026. | T6: 4
A7: 6 | B7: Agent harness | D7: 02. Agents and Harnesses | E7: 2024 | F7: 2026 | G7: Active in 2026 | H7: Beginner | I7: Yes | J7: Yes | Q7: Everything around the model that turns it into a working agent: the loop, tool definitions, permissions, sandbox, context management, memory, retries, logging and human approval gates. | R7: • Two teams using the same model can get very different results purely from harness design. • Harness setup alone can move benchmark scores by several points. • Harnesses encode assumptions about model weaknesses, so they must be revisited when models improve. | S7: Vendor harnesses (Claude Code, Codex, Gemini CLI) are now exposed as SDKs and managed runtimes so teams can build on them directly. | T7: 3
A8: 7 | B8: Harness engineering | D8: 02. Agents and Harnesses | E8: 2026 | F8: 2026 | G8: New in 2026 | H8: Intermediate | J8: Yes | Q8: The discipline that followed prompt engineering and context engineering: designing environments, constraints, documentation-as-system-of-record, structural tests and feedback loops so agents do reliable work while humans steer. | R8: • OpenAI described a team shipping a roughly million-line product with no hand-written code using this approach. • Core moves: constrain what agents can do, inform them what to do, verify their work, correct mistakes, keep humans at high-stakes gates. • Architecture rules become linters and tests the agent must pass, not wiki pages. | S8: The term entered mainstream use in early 2026 and is now the main focus of agent engineering investment. | T8: 3
A9: 8 | B9: Managed agents: decoupling brain, hands and session | D9: 02. Agents and Harnesses | E9: 2026 | F9: 2026 | G9: New in 2026 | H9: Advanced | J9: Yes | N9: Yes | Q9: An architecture where the reasoning loop (brain), the sandboxes and tools that act (hands), and the append-only event log (session) are separate, replaceable services. | R9: • The harness becomes stateless; containers are provisioned only when a tool needs them. • A crash in one sandbox does not lose the session, because state lives in the log. • Enterprises can run the hands inside their own network while the brain runs at the provider. | S9: Anthropic launched Claude Managed Agents on this design in April 2026; Cursor's cloud agents converged on a similar three-layer split. | T9: 1
A10: 9 | B10: Agentic loop / ReAct | C10: ReAct | D10: 02. Agents and Harnesses | E10: 2022 | F10: 2025 | G10: Established | H10: Beginner | I10: Yes | Q10: The basic control pattern: reason about the next step, act by calling a tool, observe the result, and loop until done. | R10: • Modern models interleave thinking between tool calls natively. • A usable coding agent loop fits in about 100 lines of code. | T10: 3
A11: 10 | B11: Workflows vs. agents | D11: 02. Agents and Harnesses | E11: 2024 | F11: 2025 | G11: Established | H11: Beginner | I11: Yes | J11: Yes | Q11: Workflows run LLM calls through predefined code paths; agents let the model direct its own process. Use the simplest pattern that works. | R11: • Common workflow patterns: prompt chaining, routing, parallelisation, orchestrator-workers, evaluator-optimiser. • Add autonomy only when the path cannot be predicted in advance. | T11: 2
A12: 11 | B12: Tool use / function calling | D12: 02. Agents and Harnesses | E12: 2023 | F12: 2025 | G12: Established | H12: Beginner | I12: Yes | Q12: Models emit structured calls (a tool name plus JSON arguments) that the harness executes and returns. Tool design is API design for a non-human user. | R12: • Prefer few, expressive tools over many narrow ones. • Return compact, high-signal output and actionable error messages. • Namespacing and clear descriptions reduce wrong-tool calls. | T12: 2
A13: 12 | B13: Tool search and programmatic tool calling | C13: code mode | D13: 02. Agents and Harnesses | E13: 2025 | F13: 2026 | G13: Active in 2026 | H13: Intermediate | J13: Yes | P13: Yes | Q13: Two fixes for tool overload. Tool search loads tool definitions on demand; programmatic tool calling lets the model write a script that calls many tools and returns only the final result. | R13: • Cuts context use and round-trips dramatically for large tool sets. • Deferred tool discovery and stable tool ordering also protect prompt-cache hits. | S13: Now a standard feature in frontier harnesses; MCP servers are increasingly consumed through code rather than direct calls. | T13: 3
A14: 13 | B14: Multi-agent systems and subagents | C14: orchestrator-worker | D14: 02. Agents and Harnesses | E14: 2023 | F14: 2026 | G14: Active in 2026 | H14: Intermediate | J14: Yes | Q14: A lead agent plans and delegates to subagents with their own clean context windows, then combines condensed results. | R14: • Great for broad research and big codebases; costs more tokens. • Specialised orchestrator models can route work between tools, small models and large models. | S14: Agent teams, swarms and parallel agents in isolated worktrees are routine in 2026 coding tools. | T14: 3
A15: 14 | B15: Long-running and background agents | D15: 02. Agents and Harnesses | E15: 2025 | F15: 2026 | G15: Active in 2026 | H15: Intermediate | J15: Yes | Q15: Agents that work for hours or days across many context windows, usually in the cloud while the human does something else. | R15: • Rely on plan files, progress notes, git history, test gates and compaction. • Early models showed context anxiety (wrapping up early near the limit); newer models largely don't, so harness workarounds can become dead weight. | S15: METR's time-horizon measure keeps doubling; multi-hour autonomous runs are normal for frontier models. | T15: 2
A16: 15 | B16: Computer use and browser agents | C16: CUA | D16: 02. Agents and Harnesses | E16: 2024 | F16: 2026 | G16: Active in 2026 | H16: Intermediate | J16: Yes | Q16: Agents that operate a GUI from screenshots with mouse and keyboard actions, or drive a browser through the DOM and accessibility tree. | R16: • Agentic browsers embed this directly in the browser. • Prompt injection from web content is the main security risk. | T16: 4
A17: 16 | B17: Personal agents | C17: OpenClaw | D17: 02. Agents and Harnesses | E17: 2026 | F17: 2026 | G17: New in 2026 | H17: Beginner | L17: Yes | O17: Yes | Q17: Always-on assistants connected to messaging apps, email, calendars and files that take real actions for a person. | R17: • OpenClaw's viral open-source spread in early 2026 put millions of personal agents into daily use. • Exposed the permission, isolation and injection problems of agents with broad personal access. | T17: 2
A18: 17 | B18: Agent sandboxes | D18: 02. Agents and Harnesses | E18: 2024 | F18: 2026 | G18: Active in 2026 | H18: Intermediate | J18: Yes | O18: Yes | Q18: Isolated environments (containers, microVMs, V8 isolates, OS-level sandboxes) where agents run code without endangering the host. | R18: • Filesystem boundaries and network egress controls are the two key levers. • Good sandboxing reduces approval fatigue: fewer prompts, more safety. | S18: Providers now let enterprises run agent sandboxes in their own clouds while the model runs remotely. | T18: 4
A19: 18 | B19: Agent frameworks and SDKs | D19: 02. Agents and Harnesses | E19: 2023 | F19: 2026 | G19: Active in 2026 | H19: Beginner | L19: Yes | Q19: Libraries that package the loop, tools, memory, handoffs and tracing. | R19: • Vendor SDKs expose the same harness their own products use. • Open frameworks add graphs, durable execution and multi-agent patterns. | T19: 8
A20: 19 | B20: Durable execution and agent trajectories | D20: 02. Agents and Harnesses | E20: 2024 | F20: 2026 | G20: Active in 2026 | H20: Advanced | J20: Yes | Q20: Persist every step so an agent can crash, pause for approval or wait days, then resume. Trajectory logs also feed memory, evals and training. | R20: • Workflow engines like Temporal are used as agent backbones. • Libraries now normalise session transcripts from many harnesses into one format. | T20: 2
A21: 20 | B21: Model Context Protocol | C21: MCP | D21: 03. Protocols and Interoperability Standards | E21: 2024 | F21: 2026 | G21: Active in 2026 | H21: Beginner | I21: Yes | M21: Yes | Q21: An open JSON-RPC protocol connecting AI applications (clients) to tools, resources and prompts exposed by servers. The de facto standard for tool integration across vendors. | R21: • 2026-07-28 revision: stateless core (no sessions or initialize handshake), server discovery on demand, cacheable list results, header-based routing. • Formal Extensions framework; MCP Apps and Tasks ship as extensions. • Authorization aligned with OAuth/OIDC: issuer validation, Client ID Metadata Documents, enterprise-managed authorization. | S21: The 2026-07-28 spec is the largest revision since launch, with a 12-month deprecation policy and SDK conformance tiers. | T21: 5
A22: 21 | B22: MCP Apps | D22: 03. Protocols and Interoperability Standards | E22: 2025 | F22: 2026 | G22: Active in 2026 | H22: Intermediate | M22: Yes | Q22: An MCP extension that lets servers return interactive UI rendered in a sandboxed frame, so tools can show forms, charts and pickers inside the chat. | R22: • Standardised as an extension in the 2026-07-28 release. | T22: 1
A23: 22 | B23: MCP Tasks | D23: 03. Protocols and Interoperability Standards | E23: 2025 | F23: 2026 | G23: Active in 2026 | H23: Intermediate | M23: Yes | Q23: An extension for long-running work: a server can accept a job, stream progress and let the client check back or steer mid-flight. | R23: • Paired with subscriptions and progress notifications for push-style updates. | T23: 1
A24: 23 | B24: Agent2Agent protocol | C24: A2A | D24: 03. Protocols and Interoperability Standards | E24: 2025 | F24: 2026 | G24: Active in 2026 | H24: Intermediate | M24: Yes | Q24: An open protocol under the Linux Foundation for agents from different vendors to discover each other via Agent Cards, exchange tasks and stream results. | R24: • MCP is agent-to-tool; A2A is agent-to-agent. | T24: 2
A25: 24 | B25: Agentic AI Foundation | C25: AAIF | D25: 03. Protocols and Interoperability Standards | E25: 2025 | F25: 2026 | G25: Active in 2026 | H25: Beginner | M25: Yes | Q25: A Linux Foundation home for vendor-neutral agent standards, founded December 2025 with MCP, AGENTS.md and goose. | R25: • Neutral governance so no single vendor controls core agent standards. • Hosts specs, reference implementations and working groups. | T25: 2
A26: 25 | B26: Agent Skills | C26: SKILL.md | D26: 03. Protocols and Interoperability Standards | E26: 2025 | F26: 2026 | G26: Active in 2026 | H26: Beginner | J26: Yes | M26: Yes | Q26: Folders with a SKILL.md (name, description, instructions) plus optional scripts that an agent loads only when relevant (progressive disclosure). | R26: • Published as an open standard; the same skill works across agent products. • Cheap way to package team know-how, house style and workflows. | T26: 3
A27: 26 | B27: AGENTS.md | D27: 03. Protocols and Interoperability Standards | E27: 2025 | F27: 2026 | G27: Active in 2026 | H27: Beginner | M27: Yes | Q27: A Markdown file at the repo root telling coding agents how to build, test and follow conventions: a README for agents. | R27: • CLAUDE.md plays the same role in Claude Code. | T27: 2
A28: 27 | B28: Agent Client Protocol | C28: ACP | D28: 03. Protocols and Interoperability Standards | E28: 2025 | F28: 2026 | G28: Active in 2026 | H28: Intermediate | M28: Yes | Q28: An editor-to-agent protocol similar in spirit to LSP, so any coding agent can plug into any editor. | R28: • Editors act as clients; agents run as subprocesses speaking JSON-RPC. • Lets one agent work in Zed, JetBrains, Neovim and others without per-editor plugins. | T28: 2
A29: 28 | B29: AG-UI | D29: 03. Protocols and Interoperability Standards | E29: 2025 | F29: 2025 | G29: Established | H29: Intermediate | M29: Yes | Q29: An event-based protocol for streaming agent state, tool calls and UI updates between backends and frontends. | R29: • Streams typed events: text deltas, tool calls, state patches, human-input requests. • Complements MCP (tools) and A2A (agents) on the user-facing side. | T29: 2
A30: 29 | B30: Agentic commerce protocols | C30: ACP, AP2, UCP, x402 | D30: 03. Protocols and Interoperability Standards | E30: 2025 | F30: 2026 | G30: Active in 2026 | H30: Intermediate | M30: Yes | N30: Yes | Q30: Standards that let agents shop and pay for users: checkout (Agentic Commerce Protocol), verifiable payment mandates (AP2), merchant integration (UCP) and machine-to-machine payments over HTTP 402 (x402). | R30: • Mandates prove the user authorised a purchase. • x402 enables per-request payments between agents and APIs. | T30: 4
A31: 30 | B31: llms.txt | D31: 03. Protocols and Interoperability Standards | E31: 2024 | F31: 2025 | G31: Established | H31: Beginner | M31: Yes | Q31: A proposed file at a website root that gives LLMs a curated Markdown map of the site's most useful content. | R31: • Plain Markdown with links and short descriptions. • Often paired with .md versions of docs pages for clean agent reading. | T31: 1
A32: 31 | B32: OpenTelemetry GenAI conventions | C32: OTel GenAI | D32: 03. Protocols and Interoperability Standards | E32: 2024 | F32: 2026 | G32: Active in 2026 | H32: Intermediate | J32: Yes | M32: Yes | Q32: Standard span and attribute names for LLM calls, tokens, tool invocations and agent steps, so traces from any framework land in any backend. | R32: • Standard attributes for model name, token counts, prompts and tool calls. • Supported by most LLMOps tools and agent SDKs. | T32: 1
A33: 32 | B33: Coding agents | D33: 04. Agentic Coding and Developer Workflow | E33: 2024 | F33: 2026 | G33: Active in 2026 | H33: Beginner | J33: Yes | L33: Yes | Q33: Terminal, IDE, desktop and cloud agents that read a repo, edit files, run commands and tests, and open pull requests. | R33: • They differ mostly in harness, permissions and UX, not the loop itself. • Cross-vendor plugins appeared: e.g. a Codex plugin for Claude Code. | S33: Claude Code, Codex, Gemini CLI, Cursor, Google Antigravity and open tools like OpenHands and OpenCode are the main options in 2026. | T33: 6
A34: 33 | B34: Vibe coding | D34: 04. Agentic Coding and Developer Workflow | E34: 2025 | F34: 2025 | G34: Established | H34: Beginner | Q34: Coined by Andrej Karpathy: building software by describing it and accepting AI output without reading it closely. Fine for prototypes, risky for production. | R34: • Useful for throwaway prototypes, personal tools and learning. • Unreviewed code carries security and maintenance risk in production. | T34: 2
A35: 34 | B35: Agentic engineering / Software 3.0 | D35: 04. Agentic Coding and Developer Workflow | E35: 2025 | F35: 2026 | G35: Active in 2026 | H35: Intermediate | J35: Yes | Q35: The professional counterpart to vibe coding: engineers specify intent, design constraints and review outcomes while agents write most of the code. | R35: • Humans steer, agents execute. • Prompts in English become a new kind of program (Software 3.0). | T35: 2
A36: 35 | B36: Spec-driven development | C36: SDD | D36: 04. Agentic Coding and Developer Workflow | E36: 2025 | F36: 2026 | G36: Active in 2026 | H36: Intermediate | J36: Yes | Q36: Write a structured spec and plan first, then let agents implement against it, keeping the spec as source of truth. | R36: • Typical flow: specify, plan, break into tasks, implement, verify. • The spec doubles as durable context for future agent sessions. | T36: 2
A37: 36 | B37: Ralph loop | C37: Ralph Wiggum technique | D37: 04. Agentic Coding and Developer Workflow | E37: 2025 | F37: 2026 | G37: Active in 2026 | H37: Intermediate | Q37: Running a coding agent in a simple while-loop against the same prompt and plan file until the job is done. | R37: • Progress lives in files and git, not in the context window. • Works best with strong tests so each iteration can check its own work. | T37: 1
A38: 37 | B38: Hooks, plugins and slash commands | D38: 04. Agentic Coding and Developer Workflow | E38: 2025 | F38: 2026 | G38: Active in 2026 | H38: Intermediate | J38: Yes | Q38: Extension points in coding agents: hooks run deterministic scripts at lifecycle events; plugins bundle commands, subagents, skills, hooks and MCP servers. | R38: • Hooks enforce rules deterministically (formatters, linters, blocked commands). • Plugins make a team's setup installable in one step. | T38: 2
A39: 38 | B39: Parallel agents with git worktrees | D39: 04. Agentic Coding and Developer Workflow | E39: 2025 | F39: 2026 | G39: Active in 2026 | H39: Intermediate | J39: Yes | Q39: Run several agents at once, each in its own worktree or container, then review and merge. | R39: • Each agent gets its own branch and working directory, avoiding conflicts. • The human shifts from typing to dispatching and reviewing. | T39: 2
A40: 39 | B40: The review bottleneck | D40: 04. Agentic Coding and Developer Workflow | E40: 2026 | F40: 2026 | G40: New in 2026 | H40: Intermediate | J40: Yes | Q40: When code generation gets cheap, human review becomes the constraint. Changes grow larger and harder to review, and plausible-looking AI code hides subtle bugs. | R40: • Mitigations: agent reviewers, architecture rules as tests, smaller PRs, agents that exercise the app themselves. | T40: 1
A41: 40 | B41: Context engineering | D41: 05. Context, Memory and Retrieval | E41: 2025 | F41: 2026 | G41: Active in 2026 | H41: Beginner | I41: Yes | J41: Yes | Q41: Curating the smallest set of high-signal tokens (instructions, tools, examples, retrieved data, history) that the model needs for its next step. | R41: • Successor to prompt engineering for agents. • Techniques: just-in-time retrieval, compaction, structured notes, subagents with clean context. | T41: 2
A42: 41 | B42: Context rot | D42: 05. Context, Memory and Retrieval | E42: 2025 | F42: 2025 | G42: Established | H42: Beginner | K42: Yes | Q42: Accuracy degrades as input length grows, even well within the advertised window. Long context is not free. | R42: • Distractors and similar-but-wrong passages hurt more than raw length. • Mitigate with retrieval, summarisation and subagents. | S42: Million-token windows are standard in 2026, but focused context still usually beats more context. | T42: 1
A43: 42 | B43: Compaction and context editing | D43: 05. Context, Memory and Retrieval | E43: 2025 | F43: 2026 | G43: Active in 2026 | H43: Intermediate | J43: Yes | Q43: Summarising or pruning old turns and stale tool results as a conversation nears the limit, so agents can keep working indefinitely. | R43: • Clear old tool outputs first; they are usually the largest and least useful. • Keep decisions, open problems and file paths in the summary. | T43: 1
A44: 43 | B44: Prompt caching | D44: 05. Context, Memory and Retrieval | E44: 2024 | F44: 2026 | G44: Active in 2026 | H44: Intermediate | J44: Yes | P44: Yes | Q44: Reusing the computed KV cache for a repeated prefix across requests to cut latency and cost. | R44: • Harnesses keep prefixes stable (tool order, system prompt) so caches keep hitting. | S44: Cache-read prices were cut steeply again in 2026, making long agent sessions much cheaper. | T44: 1
A45: 44 | B45: Agent memory | D45: 05. Context, Memory and Retrieval | E45: 2023 | F45: 2026 | G45: Active in 2026 | H45: Intermediate | J45: Yes | K45: Yes | Q45: Persisting facts, preferences and lessons beyond one context window: files the agent writes, vector or graph stores, or self-editing memory blocks. | R45: • Memory quality, provenance and forgetting are now evaluated directly. • Related to continual learning, but done outside the weights. | T45: 3
A46: 45 | B46: Retrieval-augmented generation | C46: RAG | D46: 05. Context, Memory and Retrieval | E46: 2020 | F46: 2026 | G46: Active in 2026 | H46: Beginner | I46: Yes | J46: Yes | Q46: Fetch relevant documents and put them in context before generating. | R46: • Modern stacks: hybrid BM25 + vector search, rerankers, contextual chunk headers, query rewriting. | T46: 3
A47: 46 | B47: Agentic search and deep research | D47: 05. Context, Memory and Retrieval | E47: 2025 | F47: 2026 | G47: Active in 2026 | H47: Intermediate | J47: Yes | Q47: The agent plans queries, reads pages, follows leads and synthesises a cited report over many minutes. | R47: • Many teams prefer agentic grep/file search over vector RAG for code. | T47: 2
A48: 47 | B48: GraphRAG | D48: 05. Context, Memory and Retrieval | E48: 2024 | F48: 2025 | G48: Established | H48: Intermediate | Q48: Build a knowledge graph from a corpus, then retrieve over communities and paths to answer global questions. | R48: • Entity and relation extraction with an LLM, then community summaries. • More expensive to index than vector RAG. | T48: 2
A49: 48 | B49: Embeddings, late interaction and Matryoshka | D49: 05. Context, Memory and Retrieval | E49: 2020 | F49: 2025 | G49: Established | H49: Intermediate | Q49: Dense embeddings map text to vectors; late-interaction models keep per-token vectors; Matryoshka embeddings can be truncated with little loss. | R49: • Choose embeddings by your domain and language, not only leaderboard rank. • Rerankers usually give the biggest quality jump after the first retrieval. | T49: 3
A50: 49 | B50: Structured outputs and constrained decoding | D50: 05. Context, Memory and Retrieval | E50: 2023 | F50: 2025 | G50: Established | H50: Intermediate | J50: Yes | Q50: Force output to match a JSON schema or grammar by masking invalid tokens during decoding. | R50: • Grammar engines compile schemas into token masks for near-zero overhead. • Guarantees valid syntax, not correct content. | T50: 3
A51: 50 | B51: Reasoning models and test-time compute | D51: 06. Reasoning and Post-Training | E51: 2024 | F51: 2026 | G51: Active in 2026 | H51: Beginner | I51: Yes | Q51: Models trained to think in long chains before answering; accuracy scales with thinking tokens, a second scaling axis beyond model size. | R51: • Techniques: long chain-of-thought, self-verification, parallel sampling with voting. • More thinking helps most on math, code and multi-step planning. | S51: In 2026 general and reasoning lines have merged: one model decides how much to think per request. | T51: 3
A52: 51 | B52: Thinking budgets, adaptive thinking and effort | D52: 06. Reasoning and Post-Training | E52: 2025 | F52: 2026 | G52: Active in 2026 | H52: Intermediate | J52: Yes | P52: Yes | Q52: Controls that set how much a model thinks per request, trading latency and cost for quality. Interleaved thinking lets it reason between tool calls. | R52: • Low effort for chat and simple tool calls; high for hard debugging or proofs. • Interleaved thinking helps agents adjust after each tool result. | S52: Adjustable reasoning effort inside a conversation became a standard API feature in 2026. | T52: 2
A53: 52 | B53: RL with verifiable rewards | C53: RLVR | D53: 06. Reasoning and Post-Training | E53: 2024 | F53: 2026 | G53: Active in 2026 | H53: Intermediate | I53: Yes | Q53: Reinforcement learning where rewards come from checkers (tests, answer matching, verifiers) instead of a learned preference model. | R53: • Coined in the Tulu 3 work (2024), popularised by DeepSeek-R1. • RL is now a large and growing share of frontier training compute. | T53: 2
A54: 53 | B54: Multi-teacher on-policy distillation | C54: MOPD | D54: 06. Reasoning and Post-Training | E54: 2026 | F54: 2026 | G54: New in 2026 | H54: Advanced | K54: Yes | Q54: The 2026 post-training pattern: train several domain specialists with SFT then RL, then train one general student on its own samples while minimising reverse-KL to the relevant teacher token by token. | R54: • Avoids capability trade-offs from mixing math, code and agentic RL in one run. • Specialists can be built in parallel by different teams. • Introduced with Xiaomi MiMo, scaled to 10+ teachers by DeepSeek V4 and Nemotron 3 Ultra. | S54: Now the default final stage in several frontier open recipes. | T54: 3
A55: 54 | B55: GRPO and its successors | C55: GRPO, DAPO, GSPO | D55: 06. Reasoning and Post-Training | E55: 2024 | F55: 2025 | G55: Established | H55: Advanced | K55: Yes | Q55: Group Relative Policy Optimization drops PPO's value network and scores samples against their group. Successors fix length bias, clipping and MoE instability. | R55: • Sample a group of answers per prompt; advantage = reward minus group mean. • No critic network means less memory and simpler training. | T55: 4
A56: 55 | B56: RL environments and verifiers | D56: 06. Reasoning and Post-Training | E56: 2025 | F56: 2026 | G56: Active in 2026 | H56: Advanced | K56: Yes | N56: Yes | Q56: Packaged tasks plus graders used to train agents. In 2026 environments look like sandboxed replicas of enterprise software, and verifier quality is seen as the next ceiling on agent progress. | R56: • Labs spend heavily on environments; a market of environment vendors has formed. • As agents improve, verifiers must improve faster to avoid reward hacking. | T56: 5
A57: 56 | B57: RLHF, DPO and preference optimization | D57: 06. Reasoning and Post-Training | E57: 2022 | F57: 2025 | G57: Established | H57: Intermediate | I57: Yes | Q57: Aligning outputs to human preferences with a reward model plus RL, or directly from preference pairs (DPO). | R57: • RLHF: SFT, then reward model, then PPO. • DPO optimises the same objective in closed form from preference pairs. | T57: 3
A58: 57 | B58: Constitutional AI and model specs | D58: 06. Reasoning and Post-Training | E58: 2022 | F58: 2026 | G58: Active in 2026 | H58: Intermediate | Q58: Training behaviour from a written set of principles with AI feedback. Labs now publish the documents that define model character and priorities. | R58: • The model critiques and revises its own outputs against principles. • Published specs make intended behaviour inspectable. | T58: 2
A59: 58 | B59: Process reward models | C59: PRM | D59: 06. Reasoning and Post-Training | E59: 2023 | F59: 2025 | G59: Established | H59: Advanced | K59: Yes | Q59: Reward models that grade each reasoning step rather than only the final answer. | R59: • Enable step-level search (beam search over reasoning steps). • Expensive to label; often trained with automated step checks. | T59: 1
A60: 59 | B60: Reward hacking | D60: 06. Reasoning and Post-Training | E60: 2016 | F60: 2026 | G60: Active in 2026 | H60: Intermediate | K60: Yes | O60: Yes | Q60: The policy exploits flaws in the reward (special-casing tests, editing graders) instead of solving the task; learned hacking can generalise to broader misbehaviour. | R60: • Watch for tests being deleted, asserts weakened or outputs hard-coded. • Defenses: held-out verifiers, monitoring, diverse environments. | T60: 2
A61: 60 | B61: Self-play and self-generated curricula | D61: 06. Reasoning and Post-Training | E61: 2025 | F61: 2025 | G61: Established | H61: Advanced | K61: Yes | Q61: Models propose tasks, solve them and learn from verified results. | R61: • A proposer creates tasks near the solver's frontier. • Verification (code execution, math checkers) keeps it grounded. | T61: 1
A62: 61 | B62: Continual learning | D62: 06. Reasoning and Post-Training | E62: 2024 | F62: 2026 | G62: Active in 2026 | H62: Advanced | K62: Yes | Q62: Updating a deployed model with new knowledge and skills without catastrophic forgetting. | R62: • Approaches: replay, regularisation, architectural expansion, self-distillation, nested optimisation. • Widely named as a key 2026 frontier for agents that improve on the job. | T62: 2
A63: 62 | B63: Mixture of Experts | C63: MoE | D63: 07. Model Architectures | E63: 2017 | F63: 2026 | G63: Active in 2026 | H63: Beginner | I63: Yes | P63: Yes | Q63: Tokens route to a few expert feed-forward blocks out of many, so total parameters grow while compute per token stays small. | R63: • Fine-grained experts plus a shared expert is the common 2026 layout. • Expert parallelism needs fast all-to-all communication. | S63: Frontier open models reach 1.6T to 2.8T total parameters with roughly 3% active per token. | T63: 3
A64: 63 | B64: GQA and Multi-head Latent Attention | C64: GQA, MLA | D64: 07. Model Architectures | E64: 2023 | F64: 2025 | G64: Established | H64: Intermediate | P64: Yes | Q64: Two ways to shrink the KV cache: share keys/values across head groups (GQA) or compress them into a low-rank latent (MLA). | R64: • GQA: fewer KV heads than query heads. • MLA: store a small latent, up-project at attention time; decoupled RoPE dims. | T64: 2
A65: 64 | B65: Sparse and compressed attention | C65: NSA, DSA, CSA, HCA | D65: 07. Model Architectures | E65: 2025 | F65: 2026 | G65: Active in 2026 | H65: Advanced | K65: Yes | P65: Yes | Q65: Attend only to selected tokens or compressed summaries of blocks to make long context cheap. | R65: • DeepSeek V4 interleaves Compressed Sparse Attention (compress KV along the sequence, then top-k select) with Heavily Compressed Attention. • Reported KV-cache reductions near 98% versus standard GQA make 1M-token inference affordable. | S65: DeepSeek V4's CSA/HCA hybrid replaced MLA and is the most detailed public long-context design in 2026. | T65: 3
A66: 65 | B66: Manifold-constrained hyper-connections | C66: mHC | D66: 07. Model Architectures | E66: 2026 | F66: 2026 | G66: New in 2026 | H66: Advanced | K66: Yes | Q66: Replaces plain residual connections with learned mixtures over several parallel residual streams, projected onto a constrained manifold to keep signals stable in very deep, very large models. | R66: • Used in DeepSeek V4 to stabilise training at trillion-parameter scale. | T66: 1
A67: 66 | B67: Hybrid linear-attention and state space models | C67: Mamba, Gated DeltaNet | D67: 07. Model Architectures | E67: 2023 | F67: 2026 | G67: Active in 2026 | H67: Advanced | K67: Yes | P67: Yes | Q67: Mix a few full-attention layers with many linear-time layers for long context at lower cost. | R67: • Linear layers keep a fixed-size state instead of a growing KV cache. • A few full-attention layers preserve precise recall. | S67: A leading 2026 trend: Qwen 3.x, Nemotron 3, Kimi Linear and others ship hybrids. | T67: 4
A68: 67 | B68: Diffusion language models | C68: dLLM | D68: 07. Model Architectures | E68: 2025 | F68: 2026 | G68: Active in 2026 | H68: Advanced | K68: Yes | P68: Yes | Q68: Generate text by iteratively denoising blocks in parallel rather than left to right, for much faster decoding. | R68: • Start from masked or noisy tokens and refine in parallel steps. • Trade-offs: quality on long reasoning, variable-length output. | S68: Commercial diffusion LLMs now offer very low-cost, high-speed endpoints. | T68: 3
A69: 68 | B69: Multi-token prediction and speculative decoding | C69: MTP | D69: 07. Model Architectures | E69: 2023 | F69: 2026 | G69: Active in 2026 | H69: Intermediate | P69: Yes | Q69: Predict several tokens at once, or let a cheap draft propose tokens that the big model verifies in one pass. | R69: • Draft models, extra prediction heads (MTP, Medusa, EAGLE) or n-gram lookup. • Output distribution is unchanged when verification is exact. | T69: 3
A70: 69 | B70: Long-context methods | C70: RoPE, YaRN | D70: 07. Model Architectures | E70: 2021 | F70: 2026 | G70: Active in 2026 | H70: Intermediate | Q70: Rotary embeddings and scaling tricks that extend context windows; combined with sparse attention and KV compression to reach 1M tokens. | R70: • Train short, extend with RoPE scaling plus long-context fine-tuning. • Needle tests are easy; multi-hop reasoning over long input is hard. | S70: 1M-token context is the default for 2026 frontier models. | T70: 2
A71: 70 | B71: Attention sinks | D71: 07. Model Architectures | E71: 2023 | F71: 2025 | G71: Established | H71: Advanced | K71: Yes | Q71: Models park attention on the first tokens; keeping them (or learned sink logits) stabilises long generation. | R71: • Keep the first few tokens when using sliding-window caches. • Some models add explicit sink parameters per head. | T71: 1
A72: 71 | B72: Tokenizer-free and byte-level models | C72: BLT | D72: 07. Model Architectures | E72: 2024 | F72: 2025 | G72: Established | H72: Advanced | K72: Yes | Q72: Operate on bytes grouped into dynamic patches instead of a fixed vocabulary. | R72: • Patch boundaries adapt to entropy, spending compute on hard bytes. • Improves robustness on typos, code and rare scripts. | T72: 1
A73: 72 | B73: Tiny recursive reasoning models | C73: HRM, TRM | D73: 07. Model Architectures | E73: 2025 | F73: 2025 | G73: Established | H73: Advanced | K73: Yes | Q73: Very small networks that loop over latent state, scoring well on puzzles like ARC-AGI with a few million parameters. | R73: • Iterate a small network many times on its own latent answer. • Shows depth-through-recursion can substitute for parameters on some tasks. | T73: 2
A74: 73 | B74: Small language models | C74: SLM | D74: 07. Model Architectures | E74: 2024 | F74: 2026 | G74: Active in 2026 | H74: Beginner | L74: Yes | P74: Yes | Q74: Compact models (about 0.5B to 30B) for on-device use, low latency and cheap agent subtasks. | R74: • Often distilled from large teachers. • Good fits: routing, extraction, classification, on-device assistants. | S74: 2026 mid-size open models (around 27B) deliver frontier-like coding on a single consumer GPU. | T74: 2
A75: 74 | B75: Architecture overviews | D75: 07. Model Architectures | E75: 2025 | F75: 2026 | G75: Active in 2026 | H75: Beginner | Q75: Side-by-side walkthroughs of how current open models differ. | R75: • Compare norms, attention type, expert counts, positional schemes. • Read tech reports for data and training details that diagrams omit. | T75: 2
A76: 75 | B76: Parallelism strategies | C76: DP, FSDP, TP, PP, EP, CP | D76: 08. Training at Scale and Fine-Tuning | E76: 2019 | F76: 2026 | G76: Active in 2026 | H76: Advanced | I76: Yes | Q76: Data, fully-sharded, tensor, pipeline, expert and context parallelism split models and data across devices; real runs combine several. | R76: • FSDP shards parameters, gradients and optimizer state. • Tensor and expert parallelism need fast scale-up links; pipeline tolerates slower links. | T76: 5
A77: 76 | B77: Scaling laws | D77: 08. Training at Scale and Fine-Tuning | E77: 2020 | F77: 2026 | G77: Active in 2026 | H77: Intermediate | I77: Yes | Q77: Empirical power laws relating loss to parameters, data and compute; now also studied for RL and test-time compute. | R77: • Compute-optimal data-to-parameter ratio was roughly 20 tokens per parameter (Chinchilla). • Inference cost now pushes teams to over-train smaller models. | T77: 2
A78: 77 | B78: Muon and modern optimizers | D78: 08. Training at Scale and Fine-Tuning | E78: 2024 | F78: 2026 | G78: Active in 2026 | H78: Advanced | K78: Yes | Q78: Muon orthogonalises momentum updates for matrix parameters and trains faster than AdamW at scale. | R78: • Newton-Schulz iterations approximate orthogonalisation cheaply. • Usually combined with AdamW for embeddings and norms. | S78: Adopted in frontier open models including Kimi K2 and DeepSeek V4. | T78: 3
A79: 78 | B79: Data curation and synthetic data | D79: 08. Training at Scale and Fine-Tuning | E79: 2023 | F79: 2026 | G79: Active in 2026 | H79: Intermediate | Q79: Classifier filtering, deduplication, and synthetic textbooks, reasoning traces and agent trajectories. | R79: • Quality classifiers trained on curated seed data filter web crawls. • Synthetic data risks collapse without real-data anchoring and verification. | S79: DeepSeek V4 pretrained on 32T+ tokens, more than double V3's corpus. | T79: 2
A80: 79 | B80: Mid-training | D80: 08. Training at Scale and Fine-Tuning | E80: 2024 | F80: 2026 | G80: Active in 2026 | H80: Intermediate | Q80: A stage between pretraining and post-training that shifts the mix toward code, math, long context and reasoning. | R80: • Often includes long-context extension and instruction-like data. • Sets up the base model for efficient RL later. | T80: 1
A81: 80 | B81: LoRA and parameter-efficient fine-tuning | C81: PEFT, LoRA, QLoRA | D81: 08. Training at Scale and Fine-Tuning | E81: 2021 | F81: 2025 | G81: Established | H81: Intermediate | P81: Yes | Q81: Train small low-rank adapters instead of all weights; QLoRA does it on a 4-bit base. | R81: • Adapters are small files you can swap per customer or task. • Higher ranks and all-layer adapters close most of the gap to full fine-tuning. | T81: 4
A82: 81 | B82: Fine-tuning toolkits and APIs | D82: 08. Training at Scale and Fine-Tuning | E82: 2023 | F82: 2026 | G82: Active in 2026 | H82: Beginner | L82: Yes | Q82: Tools that make SFT, DPO and RL fine-tuning accessible on one GPU or as a managed API. | R82: • Start with SFT on a few thousand good examples before trying RL. • Managed APIs hide distributed training but constrain algorithms. | T82: 4
A83: 82 | B83: Model merging | D83: 08. Training at Scale and Fine-Tuning | E83: 2023 | F83: 2025 | G83: Established | H83: Intermediate | Q83: Combining weights of several fine-tunes (SLERP, TIES, DARE) without further training. | R83: • Works best between fine-tunes of the same base model. • Popular for combining skills or languages cheaply. | T83: 1
A84: 83 | B84: Decentralized training | C84: DiLoCo | D84: 08. Training at Scale and Fine-Tuning | E84: 2023 | F84: 2026 | G84: Active in 2026 | H84: Advanced | K84: Yes | Q84: Training across loosely connected clusters that synchronise rarely. | R84: • Workers train locally for many steps, then average updates. • Enables training across datacenters and volunteer compute. | T84: 2
A85: 84 | B85: Build-it-yourself references | D85: 08. Training at Scale and Fine-Tuning | E85: 2023 | F85: 2026 | G85: Active in 2026 | H85: Beginner | L85: Yes | Q85: Minimal end-to-end codebases for learning how chat models are trained. | R85: • nanochat trains a small ChatGPT-like model end to end for a few hundred dollars. • CS336 covers tokenizers, kernels, scaling and alignment from scratch. | T85: 2
A86: 85 | B86: Inference engines | D86: 09. Inference and Serving | E86: 2023 | F86: 2026 | G86: Active in 2026 | H86: Beginner | J86: Yes | L86: Yes | Q86: Servers that batch requests, manage the KV cache and run optimised kernels. | R86: • Pick by hardware, model support and features (disaggregation, LoRA, structured output). • Benchmark on your own traffic shape. | S86: vLLM and SGLang lead open serving; llama.cpp, Ollama and MLX dominate local use. | T86: 6
A87: 86 | B87: KV cache and PagedAttention | D87: 09. Inference and Serving | E87: 2023 | F87: 2025 | G87: Established | H87: Intermediate | I87: Yes | Q87: Keys and values of past tokens are cached; PagedAttention stores them in fixed pages like virtual memory. | R87: • KV memory grows with batch size times sequence length. • Paging enables sharing and near-zero waste. | T87: 1
A88: 87 | B88: Continuous batching and prefix caching | D88: 09. Inference and Serving | E88: 2022 | F88: 2025 | G88: Established | H88: Intermediate | P88: Yes | Q88: Add and remove requests every step, and share cached prefixes (radix trees) across requests. | R88: • Keeps GPUs busy despite requests of different lengths. • Prefix sharing is huge for agents with long common system prompts. | T88: 1
A89: 88 | B89: Prefill/decode disaggregation | C89: PD disaggregation | D89: 09. Inference and Serving | E89: 2024 | F89: 2026 | G89: Active in 2026 | H89: Advanced | J89: Yes | P89: Yes | Q89: Run compute-bound prefill and memory-bound decode on separate pools, moving KV caches between them. | R89: • NVIDIA now builds separate rack types for prefill (CPX) and decode, scheduled together by Dynamo. | S89: Standard for large-scale serving of million-token contexts in 2026. | T89: 4
A90: 89 | B90: KV cache offloading | D90: 09. Inference and Serving | E90: 2024 | F90: 2026 | G90: Active in 2026 | H90: Advanced | P90: Yes | Q90: Spill KV caches to CPU memory, SSD or remote storage and reload them for later turns. | R90: • Turns re-prefill into a memory read. • Tiered storage: HBM, CPU DRAM, local SSD, network. | T90: 1
A91: 90 | B91: Attention kernels | C91: FlashAttention | D91: 09. Inference and Serving | E91: 2022 | F91: 2026 | G91: Active in 2026 | H91: Advanced | Q91: IO-aware fused attention kernels that avoid materialising the full attention matrix. | R91: • Tiling keeps data in fast on-chip SRAM. • New versions target Hopper, Blackwell and FP8/FP4 paths. | T91: 2
A92: 91 | B92: On-device and edge inference | D92: 09. Inference and Serving | E92: 2023 | F92: 2026 | G92: Active in 2026 | H92: Beginner | P92: Yes | Q92: Running models on phones, laptops and embedded hardware with quantised weights and NPU runtimes. | R92: • Privacy and offline use are the main drivers. • Memory bandwidth, not compute, limits phone and laptop token rates. | T92: 2
A93: 92 | B93: LLM gateways and routers | D93: 09. Inference and Serving | E93: 2023 | F93: 2026 | G93: Active in 2026 | H93: Beginner | J93: Yes | P93: Yes | Q93: One API over many providers with fallbacks, budgets, caching and routing to cheaper models. | R93: • Central place for keys, rate limits, logging and cost control. • Routers send easy prompts to cheap models. | T93: 2
A94: 93 | B94: Inference benchmarking | D94: 09. Inference and Serving | E94: 2025 | F94: 2026 | G94: Active in 2026 | H94: Intermediate | P94: Yes | Q94: Measuring throughput, latency and cost per million tokens across hardware and software stacks. | R94: • Report throughput at a fixed latency target. • Cost per million tokens depends on batch size and cache hit rate. | T94: 2
A95: 94 | B95: Microscaling formats | C95: MX, MXFP8, MXFP4 | D95: 10. Quantization and Number Formats | E95: 2023 | F95: 2026 | G95: Active in 2026 | H95: Advanced | M95: Yes | P95: Yes | Q95: An Open Compute Project standard: blocks of values share one scale, making 8-, 6- and 4-bit floats accurate enough for training and inference. | R95: • Shared 8-bit exponent scale per 32-element block. • Supported by NVIDIA, AMD, Intel, Arm, Meta and Microsoft. | T95: 3
A96: 95 | B96: NVFP4 | D96: 10. Quantization and Number Formats | E96: 2025 | F96: 2026 | G96: Active in 2026 | H96: Advanced | P96: Yes | Q96: NVIDIA's 4-bit float with 16-value blocks and FP8 scales, native on Blackwell and Rubin. | R96: • Smaller blocks and finer scales than MXFP4 improve accuracy. • Increasingly used for pretraining as well as inference. | S96: Rubin rack performance is quoted primarily in FP4 exaflops. | T96: 1
A97: 96 | B97: FP8 training and inference | C97: E4M3, E5M2 | D97: 10. Quantization and Number Formats | E97: 2022 | F97: 2026 | G97: Active in 2026 | H97: Intermediate | Q97: Two 8-bit float layouts used for large-scale training and routine serving; KV caches are often stored in FP8. | R97: • E4M3 for weights and activations, E5M2 for gradients. • Needs per-tensor or per-block scaling to avoid overflow. | T97: 1
A98: 97 | B98: Post-training quantization | C98: GPTQ, AWQ | D98: 10. Quantization and Number Formats | E98: 2022 | F98: 2025 | G98: Established | H98: Intermediate | P98: Yes | Q98: Compress trained weights to 4 or 8 bits using calibration data. | R98: • 4-bit weights with 16-bit activations is the common local setup. • Always re-run your evals after quantizing. | T98: 3
A99: 98 | B99: Quantization-aware training | C99: QAT | D99: 10. Quantization and Number Formats | E99: 2024 | F99: 2026 | G99: Active in 2026 | H99: Advanced | Q99: Simulate low precision during training so the model tolerates it. | R99: • Fake-quantize in the forward pass, keep full-precision master weights. • Recovers much of the accuracy lost to aggressive PTQ. | T99: 1
A100: 99 | B100: GGUF and local model formats | D100: 10. Quantization and Number Formats | E100: 2023 | F100: 2026 | G100: Active in 2026 | H100: Beginner | L100: Yes | Q100: A single-file format for quantised models used by llama.cpp and local runners. | R100: • K-quants (Q4_K_M, Q5_K_M) balance size and quality. • Metadata stores tokenizer and chat template in the file. | T100: 2
...

Sheet Resources
A1: Year | B1: Type | C1: Resource | D1: URL | E1: Concept | F1: Category | G1: Concept since | H1: Level | I1: Status
A2: 2026 | B2: Docs | C2: Anthropic: Project Glasswing | D2: https://www.anthropic.com/glasswing | E2: Mythos-class tier and trusted access | F2: 01. The Frontier Landscape (September 2026) | G2: 2026 | H2: Beginner | I2: New in 2026
A3: 2026 | B3: Docs | C3: Anthropic statement on Fable and Mythos access | D3: https://www.anthropic.com/news/fable-mythos-access | E3: Mythos-class tier and trusted access | F3: 01. The Frontier Landscape (September 2026) | G3: 2026 | H3: Beginner | I3: New in 2026
A4: 2026 | B4: Blog | C4: DataNorth: Claude Fable 5 and Mythos 5 explained | D4: https://datanorth.ai/news/anthropic-releases-claude-fable-5-and-mythos-5 | E4: Mythos-class tier and trusted access | F4: 01. The Frontier Landscape (September 2026) | G4: 2026 | H4: Beginner | I4: New in 2026
A5: 2026 | B5: Blog | C5: OpenAI: Path to Astra | D5: https://openai.com/index/path-to-astra/ | E5: GPT-6 Astra and the Critical cyber threshold | F5: 01. The Frontier Landscape (September 2026) | G5: 2026 | H5: Beginner | I5: New in 2026
A6: 2026 | B6: Docs | C6: GPT-6 Astra system card | D6: https://deploymentsafety.openai.com/gpt-6-astra | E6: GPT-6 Astra and the Critical cyber threshold | F6: 01. The Frontier Landscape (September 2026) | G6: 2026 | H6: Beginner | I6: New in 2026
A7: 2026 | B7: Blog | C7: OpenAI: Safety overview of GPT-6 Astra | D7: https://openai.com/index/safety-overview-gpt-6-astra/ | E7: GPT-6 Astra and the Critical cyber threshold | F7: 01. The Frontier Landscape (September 2026) | G7: 2026 | H7: Beginner | I7: New in 2026
A8: 2026 | B8: Blog | C8: InfoQ: Astra is first model rated Critical for cyber | D8: https://www.infoq.com/news/2026/09/gpt-6-astra-critical-cyber/ | E8: GPT-6 Astra and the Critical cyber threshold | F8: 01. The Frontier Landscape (September 2026) | G8: 2026 | H8: Beginner | I8: New in 2026
A9: 2026 | B9: Docs | C9: Anthropic: Project Glasswing | D9: https://www.anthropic.com/glasswing | E9: Tiered access for dual-use models | F9: 01. The Frontier Landscape (September 2026) | G9: 2025 | H9: Intermediate | I9: Active in 2026
A10: 2026 | B10: Blog | C10: CSO Online: Astra crosses the Critical cyber threshold | D10: https://www.csoonline.com/article/4218679/openai-launches-gpt-6-astra-its-first-model-to-cross-a-critical-cybersecurity-threshold.html | E10: Tiered access for dual-use models | F10: 01. The Frontier Landscape (September 2026) | G10: 2025 | H10: Intermediate | I10: Active in 2026
A11: 2026 | B11: Paper | C11: DeepSeek-V4 technical report | D11: https://arxiv.org/abs/2606.19348 | E11: Open-weight frontier models | F11: 01. The Frontier Landscape (September 2026) | G11: 2023 | H11: Beginner | I11: Active in 2026
A12: 2026 | B12: Blog | C12: HF blog: DeepSeek V4 architecture analysis | D12: https://huggingface.co/blog/ResterChed/deepseek-v4-ga-architecture | E12: Open-weight frontier models | F12: 01. The Frontier Landscape (September 2026) | G12: 2023 | H12: Beginner | I12: Active in 2026
A13: 2016 | B13: Docs | C13: Hugging Face models hub | D13: https://huggingface.co/models | E13: Open-weight frontier models | F13: 01. The Frontier Landscape (September 2026) | G13: 2023 | H13: Beginner | I13: Active in 2026
... A431: 2024 | B431: GitHub | C431: MCP servers | D431: https://github.com/modelcontextprotocol/servers | E431: Curated lists | F431: 17. Keep Learning: Curated Resources | G431: 2024 | H431: Beginner | I431: Active in 2026
